python_web_extras/__init__.py
python_web_extras/contrib/__init__.py
python_web_extras/contrib/encoding.py
python_web_extras/contrib/exceptions.py
python_web_extras/contrib/auth/__init__.py
python_web_extras/contrib/auth/constants.py
python_web_extras/contrib/auth/crypto.py
python_web_extras/contrib/auth/hashers.py
python_web_extras/contrib/auth/tortoise/__init__.py
python_web_extras/contrib/auth/tortoise/base_user.py
python_web_extras/contrib/utils/__init__.py
python_web_extras/contrib/utils/module_loading.py
python_web_extras/fastapi/__init__.py
python_web_extras/fastapi/api_settings.py
python_web_extras/fastapi/conf.py
python_web_extras/fastapi/hashers.py
python_web_extras/fastapi/logging.py
python_web_extras/fastapi/models.py
python_web_extras/fastapi/errors/__init__.py
python_web_extras/fastapi/errors/http_error.py
python_web_extras/fastapi/errors/validation_error.py
python_web_extras-0.1.0.dist-info/AUTHORS
python_web_extras-0.1.0.dist-info/LICENSE
python_web_extras-0.1.0.dist-info/METADATA
python_web_extras-0.1.0.dist-info/WHEEL
python_web_extras-0.1.0.dist-info/top_level.txt
python_web_extras-0.1.0.dist-info/RECORD
