Metadata-Version: 2.1
Name: python-web-extras
Version: 0.1.0
Summary: Utils for your favourite python web projects.
Home-page: https://tarsil.github.io/fastapi-utils-extra/
Author: Tiago Silva
Author-email: tiago.arasilva@gmail.com
License: MIT
Classifier: Development Status :: 5 - Production/Stable
Classifier: Environment :: Web Environment
Classifier: Framework :: Django
Classifier: Framework :: Django :: 2.2
Classifier: Framework :: Django :: 3.0
Classifier: Framework :: Django :: 3.1
Classifier: Framework :: Django :: 3.2
Classifier: Framework :: Django :: 4.0
Classifier: Intended Audience :: Developers
Classifier: License :: OSI Approved :: BSD License
Classifier: Operating System :: OS Independent
Classifier: Programming Language :: Python
Classifier: Programming Language :: Python :: 3
Classifier: Programming Language :: Python :: 3.8
Classifier: Programming Language :: Python :: 3.9
Classifier: Programming Language :: Python :: 3.10
Classifier: Programming Language :: Python :: 3 :: Only
Classifier: Topic :: Internet :: WWW/HTTP
Requires-Python: >=3.7
License-File: LICENSE
License-File: AUTHORS
Requires-Dist: fastapi (>=0.79.0)
Requires-Dist: fastapi-utils (>=0.2.1)
Requires-Dist: loguru (>=0.6.0)
Requires-Dist: quart (>=0.18.0)
Requires-Dist: passlib (==1.7.4)
Requires-Dist: pytz (==2022.1)
Requires-Dist: tortoise-orm (>=0.19.2)
